README.md
setup.py
pytorwrap/__init__.py
pytorwrap/exception.py
pytorwrap/tor.py
pytorwrap.egg-info/PKG-INFO
pytorwrap.egg-info/SOURCES.txt
pytorwrap.egg-info/dependency_links.txt
pytorwrap.egg-info/requires.txt
pytorwrap.egg-info/top_level.txt