Metadata-Version: 1.0
Name: pytorwrap
Version: 1.0
Summary: PytorWrap Module used to apply tor as proxy and renew IP.
Home-page: https://github.com/Ammadkhalid/pytorwrap
Author: Ammad Khalid
Author-email: ammadkhalid12@gmail.com
License: UNKNOWN
Platform: UNKNOWN
